<?xml version="1.0" ?>
<FlowMonitor>
  <FlowStats>
    <Flow flowId="1" timeFirstTxPacket="+0.0ns" timeFirstRxPacket="+3013933365.0ns" timeLastTxPacket="+59983767000.0ns" timeLastRxPacket="+59990937358.0ns" delaySum="+86161687762.0ns" jitterSum="+10115556747.0ns" lastDelay="+7170358.0ns" txBytes="497407" rxBytes="497351" txPackets="9431" rxPackets="9430" lostPackets="1" timesForwarded="9430">
      <delayHistogram nBins="15" >
        <bin index="6" start="0.006" width="0.001" count="1401" />
        <bin index="7" start="0.007" width="0.001" count="3448" />
        <bin index="8" start="0.008" width="0.001" count="955" />
        <bin index="9" start="0.009" width="0.001" count="686" />
        <bin index="10" start="0.01" width="0.001" count="659" />
        <bin index="11" start="0.011" width="0.001" count="595" />
        <bin index="12" start="0.012" width="0.001" count="532" />
        <bin index="13" start="0.013" width="0.001" count="562" />
        <bin index="14" start="0.014" width="0.001" count="592" />
      </delayHistogram>
      <jitterHistogram nBins="9" >
        <bin index="0" start="0" width="0.001" count="4274" />
        <bin index="1" start="0.001" width="0.001" count="4422" />
        <bin index="2" start="0.002" width="0.001" count="107" />
        <bin index="3" start="0.003" width="0.001" count="95" />
        <bin index="4" start="0.004" width="0.001" count="48" />
        <bin index="5" start="0.005" width="0.001" count="46" />
        <bin index="6" start="0.006" width="0.001" count="140" />
        <bin index="7" start="0.007" width="0.001" count="284" />
        <bin index="8" start="0.008" width="0.001" count="13" />
      </jitterHistogram>
      <packetSizeHistogram nBins="14" >
        <bin index="2" start="40" width="20" count="8964" />
        <bin index="3" start="60" width="20" count="458" />
        <bin index="12" start="240" width="20" count="1" />
        <bin index="13" start="260" width="20" count="7" />
      </packetSizeHistogram>
      <flowInterruptionsHistogram nBins="4" >
        <bin index="3" start="0.75" width="0.25" count="1" />
      </flowInterruptionsHistogram>
    </Flow>
    <Flow flowId="2" timeFirstTxPacket="+0.0ns" timeFirstRxPacket="+3013938004.0ns" timeLastTxPacket="+59946531000.0ns" timeLastRxPacket="+59956945996.0ns" delaySum="+145266280935.0ns" jitterSum="+15861943510.0ns" lastDelay="+10414996.0ns" txBytes="884118" rxBytes="884062" txPackets="16785" rxPackets="16784" lostPackets="1" timesForwarded="16784">
      <delayHistogram nBins="15" >
        <bin index="6" start="0.006" width="0.001" count="3118" />
        <bin index="7" start="0.007" width="0.001" count="6833" />
        <bin index="8" start="0.008" width="0.001" count="1600" />
        <bin index="9" start="0.009" width="0.001" count="1265" />
        <bin index="10" start="0.01" width="0.001" count="1191" />
        <bin index="11" start="0.011" width="0.001" count="885" />
        <bin index="12" start="0.012" width="0.001" count="664" />
        <bin index="13" start="0.013" width="0.001" count="617" />
        <bin index="14" start="0.014" width="0.001" count="611" />
      </delayHistogram>
      <jitterHistogram nBins="9" >
        <bin index="0" start="0" width="0.001" count="8690" />
        <bin index="1" start="0.001" width="0.001" count="6821" />
        <bin index="2" start="0.002" width="0.001" count="345" />
        <bin index="3" start="0.003" width="0.001" count="252" />
        <bin index="4" start="0.004" width="0.001" count="106" />
        <bin index="5" start="0.005" width="0.001" count="59" />
        <bin index="6" start="0.006" width="0.001" count="193" />
        <bin index="7" start="0.007" width="0.001" count="298" />
        <bin index="8" start="0.008" width="0.001" count="19" />
      </jitterHistogram>
      <packetSizeHistogram nBins="14" >
        <bin index="2" start="40" width="20" count="16044" />
        <bin index="3" start="60" width="20" count="733" />
        <bin index="12" start="240" width="20" count="1" />
        <bin index="13" start="260" width="20" count="6" />
      </packetSizeHistogram>
      <flowInterruptionsHistogram nBins="0" >
      </flowInterruptionsHistogram>
    </Flow>
    <Flow flowId="3" timeFirstTxPacket="+0.0ns" timeFirstRxPacket="+3013942643.0ns" timeLastTxPacket="+59999799000.0ns" timeLastRxPacket="+59999933039.0ns" delaySum="+118179739504.0ns" jitterSum="+12887151472.0ns" lastDelay="+7654039.0ns" txBytes="711852" rxBytes="711432" txPackets="13453" rxPackets="13445" lostPackets="1" timesForwarded="13445">
      <delayHistogram nBins="15" >
        <bin index="6" start="0.006" width="0.001" count="2418" />
        <bin index="7" start="0.007" width="0.001" count="5316" />
        <bin index="8" start="0.008" width="0.001" count="1289" />
        <bin index="9" start="0.009" width="0.001" count="973" />
        <bin index="10" start="0.01" width="0.001" count="936" />
        <bin index="11" start="0.011" width="0.001" count="727" />
        <bin index="12" start="0.012" width="0.001" count="585" />
        <bin index="13" start="0.013" width="0.001" count="579" />
        <bin index="14" start="0.014" width="0.001" count="622" />
      </delayHistogram>
      <jitterHistogram nBins="9" >
        <bin index="0" start="0" width="0.001" count="6902" />
        <bin index="1" start="0.001" width="0.001" count="5557" />
        <bin index="2" start="0.002" width="0.001" count="245" />
        <bin index="3" start="0.003" width="0.001" count="150" />
        <bin index="4" start="0.004" width="0.001" count="81" />
        <bin index="5" start="0.005" width="0.001" count="55" />
        <bin index="6" start="0.006" width="0.001" count="151" />
        <bin index="7" start="0.007" width="0.001" count="289" />
        <bin index="8" start="0.008" width="0.001" count="14" />
      </jitterHistogram>
      <packetSizeHistogram nBins="14" >
        <bin index="2" start="40" width="20" count="12619" />
        <bin index="3" start="60" width="20" count="820" />
        <bin index="12" start="240" width="20" count="1" />
        <bin index="13" start="260" width="20" count="5" />
      </packetSizeHistogram>
      <flowInterruptionsHistogram nBins="0" >
      </flowInterruptionsHistogram>
    </Flow>
    <Flow flowId="4" timeFirstTxPacket="+0.0ns" timeFirstRxPacket="+3013947282.0ns" timeLastTxPacket="+59969325000.0ns" timeLastRxPacket="+59976933039.0ns" delaySum="+119498181483.0ns" jitterSum="+13121443379.0ns" lastDelay="+7608039.0ns" txBytes="720882" rxBytes="720826" txPackets="13624" rxPackets="13623" lostPackets="1" timesForwarded="13623">
      <delayHistogram nBins="15" >
        <bin index="6" start="0.006" width="0.001" count="2394" />
        <bin index="7" start="0.007" width="0.001" count="5465" />
        <bin index="8" start="0.008" width="0.001" count="1310" />
        <bin index="9" start="0.009" width="0.001" count="1008" />
        <bin index="10" start="0.01" width="0.001" count="941" />
        <bin index="11" start="0.011" width="0.001" count="741" />
        <bin index="12" start="0.012" width="0.001" count="588" />
        <bin index="13" start="0.013" width="0.001" count="546" />
        <bin index="14" start="0.014" width="0.001" count="630" />
      </delayHistogram>
      <jitterHistogram nBins="9" >
        <bin index="0" start="0" width="0.001" count="6958" />
        <bin index="1" start="0.001" width="0.001" count="5655" />
        <bin index="2" start="0.002" width="0.001" count="245" />
        <bin index="3" start="0.003" width="0.001" count="173" />
        <bin index="4" start="0.004" width="0.001" count="74" />
        <bin index="5" start="0.005" width="0.001" count="54" />
        <bin index="6" start="0.006" width="0.001" count="164" />
        <bin index="7" start="0.007" width="0.001" count="278" />
        <bin index="8" start="0.008" width="0.001" count="21" />
      </jitterHistogram>
      <packetSizeHistogram nBins="14" >
        <bin index="2" start="40" width="20" count="12890" />
        <bin index="3" start="60" width="20" count="726" />
        <bin index="12" start="240" width="20" count="1" />
        <bin index="13" start="260" width="20" count="6" />
      </packetSizeHistogram>
      <flowInterruptionsHistogram nBins="0" >
      </flowInterruptionsHistogram>
    </Flow>
    <Flow flowId="5" timeFirstTxPacket="+39928570.0ns" timeFirstRxPacket="+39928702.0ns" timeLastTxPacket="+39928570.0ns" timeLastRxPacket="+39929098.0ns" delaySum="+1320.0ns" jitterSum="+396.0ns" lastDelay="+528.0ns" txBytes="656" rxBytes="656" txPackets="4" rxPackets="4" lostPackets="0" timesForwarded="0">
      <delayHistogram nBins="1" >
        <bin index="0" start="0" width="0.001" count="4" />
      </delayHistogram>
      <jitterHistogram nBins="1" >
        <bin index="0" start="0" width="0.001" count="3" />
      </jitterHistogram>
      <packetSizeHistogram nBins="9" >
        <bin index="8" start="160" width="20" count="4" />
      </packetSizeHistogram>
      <flowInterruptionsHistogram nBins="0" >
      </flowInterruptionsHistogram>
    </Flow>
    <Flow flowId="6" timeFirstTxPacket="+39928702.0ns" timeFirstRxPacket="+39928834.0ns" timeLastTxPacket="+39929098.0ns" timeLastRxPacket="+39929230.0ns" delaySum="+528.0ns" jitterSum="+0.0ns" lastDelay="+132.0ns" txBytes="656" rxBytes="656" txPackets="4" rxPackets="4" lostPackets="0" timesForwarded="0">
      <delayHistogram nBins="1" >
        <bin index="0" start="0" width="0.001" count="4" />
      </delayHistogram>
      <jitterHistogram nBins="1" >
        <bin index="0" start="0" width="0.001" count="3" />
      </jitterHistogram>
      <packetSizeHistogram nBins="9" >
        <bin index="8" start="160" width="20" count="4" />
      </packetSizeHistogram>
      <flowInterruptionsHistogram nBins="0" >
      </flowInterruptionsHistogram>
    </Flow>
    <Flow flowId="7" timeFirstTxPacket="+39928834.0ns" timeFirstRxPacket="+39928952.0ns" timeLastTxPacket="+39929230.0ns" timeLastRxPacket="+39929348.0ns" delaySum="+472.0ns" jitterSum="+0.0ns" lastDelay="+118.0ns" txBytes="584" rxBytes="584" txPackets="4" rxPackets="4" lostPackets="0" timesForwarded="0">
      <delayHistogram nBins="1" >
        <bin index="0" start="0" width="0.001" count="4" />
      </delayHistogram>
      <jitterHistogram nBins="1" >
        <bin index="0" start="0" width="0.001" count="3" />
      </jitterHistogram>
      <packetSizeHistogram nBins="8" >
        <bin index="7" start="140" width="20" count="4" />
      </packetSizeHistogram>
      <flowInterruptionsHistogram nBins="0" >
      </flowInterruptionsHistogram>
    </Flow>
    <Flow flowId="8" timeFirstTxPacket="+39928952.0ns" timeFirstRxPacket="+39929070.0ns" timeLastTxPacket="+39929348.0ns" timeLastRxPacket="+39929466.0ns" delaySum="+472.0ns" jitterSum="+0.0ns" lastDelay="+118.0ns" txBytes="584" rxBytes="584" txPackets="4" rxPackets="4" lostPackets="0" timesForwarded="0">
      <delayHistogram nBins="1" >
        <bin index="0" start="0" width="0.001" count="4" />
      </delayHistogram>
      <jitterHistogram nBins="1" >
        <bin index="0" start="0" width="0.001" count="3" />
      </jitterHistogram>
      <packetSizeHistogram nBins="8" >
        <bin index="7" start="140" width="20" count="4" />
      </packetSizeHistogram>
      <flowInterruptionsHistogram nBins="0" >
      </flowInterruptionsHistogram>
    </Flow>
    <Flow flowId="9" timeFirstTxPacket="+3013933365.0ns" timeFirstRxPacket="+3018999999.0ns" timeLastTxPacket="+59990937358.0ns" timeLastRxPacket="+59983767000.0ns" delaySum="+1669239163005.0ns" jitterSum="+60214095210.0ns" lastDelay="+78829642.0ns" txBytes="10829828" rxBytes="10805080" txPackets="18423" rxPackets="18380" lostPackets="15" timesForwarded="18380">
      <delayHistogram nBins="855" >
        <bin index="5" start="0.005" width="0.001" count="170" />
        <bin index="6" start="0.006" width="0.001" count="15" />
        <bin index="7" start="0.007" width="0.001" count="10" />
        <bin index="8" start="0.008" width="0.001" count="10" />
        <bin index="9" start="0.009" width="0.001" count="7" />
        <bin index="10" start="0.01" width="0.001" count="9" />
        <bin index="11" start="0.011" width="0.001" count="4" />
        <bin index="12" start="0.012" width="0.001" count="7" />
        <bin index="13" start="0.013" width="0.001" count="3" />
        <bin index="14" start="0.014" width="0.001" count="4" />
        <bin index="15" start="0.015" width="0.001" count="3" />
        <bin index="16" start="0.016" width="0.001" count="2" />
        <bin index="17" start="0.017" width="0.001" count="1" />
        <bin index="18" start="0.018" width="0.001" count="3" />
        <bin index="19" start="0.019" width="0.001" count="1" />
        <bin index="20" start="0.02" width="0.001" count="1" />
        <bin index="21" start="0.021" width="0.001" count="1" />
        <bin index="22" start="0.022" width="0.001" count="1" />
        <bin index="23" start="0.023" width="0.001" count="2" />
        <bin index="24" start="0.024" width="0.001" count="2" />
        <bin index="25" start="0.025" width="0.001" count="3" />
        <bin index="26" start="0.026" width="0.001" count="1" />
        <bin index="27" start="0.027" width="0.001" count="1" />
        <bin index="28" start="0.028" width="0.001" count="3" />
        <bin index="29" start="0.029" width="0.001" count="1" />
        <bin index="30" start="0.03" width="0.001" count="3" />
        <bin index="31" start="0.031" width="0.001" count="1" />
        <bin index="32" start="0.032" width="0.001" count="5" />
        <bin index="34" start="0.034" width="0.001" count="4" />
        <bin index="35" start="0.035" width="0.001" count="2" />
        <bin index="36" start="0.036" width="0.001" count="2" />
        <bin index="37" start="0.037" width="0.001" count="1" />
        <bin index="38" start="0.038" width="0.001" count="1" />
        <bin index="39" start="0.039" width="0.001" count="1" />
        <bin index="41" start="0.041" width="0.001" count="1" />
        <bin index="42" start="0.042" width="0.001" count="1" />
        <bin index="44" start="0.044" width="0.001" count="1" />
        <bin index="45" start="0.045" width="0.001" count="1" />
        <bin index="47" start="0.047" width="0.001" count="1" />
        <bin index="49" start="0.049" width="0.001" count="1" />
        <bin index="50" start="0.05" width="0.001" count="3" />
        <bin index="51" start="0.051" width="0.001" count="1" />
        <bin index="52" start="0.052" width="0.001" count="1" />
        <bin index="53" start="0.053" width="0.001" count="1" />
        <bin index="54" start="0.054" width="0.001" count="1" />
        <bin index="55" start="0.055" width="0.001" count="7" />
        <bin index="56" start="0.056" width="0.001" count="10" />
        <bin index="57" start="0.057" width="0.001" count="14" />
        <bin index="58" start="0.058" width="0.001" count="23" />
        <bin index="59" start="0.059" width="0.001" count="34" />
        <bin index="60" start="0.06" width="0.001" count="50" />
        <bin index="61" start="0.061" width="0.001" count="60" />
        <bin index="62" start="0.062" width="0.001" count="70" />
        <bin index="63" start="0.063" width="0.001" count="86" />
        <bin index="64" start="0.064" width="0.001" count="85" />
        <bin index="65" start="0.065" width="0.001" count="102" />
        <bin index="66" start="0.066" width="0.001" count="126" />
        <bin index="67" start="0.067" width="0.001" count="136" />
        <bin index="68" start="0.068" width="0.001" count="122" />
        <bin index="69" start="0.069" width="0.001" count="131" />
        <bin index="70" start="0.07" width="0.001" count="116" />
        <bin index="71" start="0.071" width="0.001" count="124" />
        <bin index="72" start="0.072" width="0.001" count="134" />
        <bin index="73" start="0.073" width="0.001" count="145" />
        <bin index="74" start="0.074" width="0.001" count="176" />
        <bin index="75" start="0.075" width="0.001" count="183" />
        <bin index="76" start="0.076" width="0.001" count="200" />
        <bin index="77" start="0.077" width="0.001" count="233" />
        <bin index="78" start="0.078" width="0.001" count="259" />
        <bin index="79" start="0.079" width="0.001" count="280" />
        <bin index="80" start="0.08" width="0.001" count="315" />
        <bin index="81" start="0.081" width="0.001" count="352" />
        <bin index="82" start="0.082" width="0.001" count="325" />
        <bin index="83" start="0.083" width="0.001" count="356" />
        <bin index="84" start="0.084" width="0.001" count="380" />
        <bin index="85" start="0.085" width="0.001" count="404" />
        <bin index="86" start="0.086" width="0.001" count="415" />
        <bin index="87" start="0.087" width="0.001" count="431" />
        <bin index="88" start="0.088" width="0.001" count="405" />
        <bin index="89" start="0.089" width="0.001" count="558" />
        <bin index="90" start="0.09" width="0.001" count="502" />
        <bin index="91" start="0.091" width="0.001" count="523" />
        <bin index="92" start="0.092" width="0.001" count="599" />
        <bin index="93" start="0.093" width="0.001" count="592" />
        <bin index="94" start="0.094" width="0.001" count="659" />
        <bin index="95" start="0.095" width="0.001" count="573" />
        <bin index="96" start="0.096" width="0.001" count="598" />
        <bin index="97" start="0.097" width="0.001" count="578" />
        <bin index="98" start="0.098" width="0.001" count="670" />
        <bin index="99" start="0.099" width="0.001" count="574" />
        <bin index="100" start="0.1" width="0.001" count="626" />
        <bin index="101" start="0.101" width="0.001" count="653" />
        <bin index="102" start="0.102" width="0.001" count="639" />
        <bin index="103" start="0.103" width="0.001" count="664" />
        <bin index="104" start="0.104" width="0.001" count="625" />
        <bin index="105" start="0.105" width="0.001" count="502" />
        <bin index="106" start="0.106" width="0.001" count="403" />
        <bin index="107" start="0.107" width="0.001" count="499" />
        <bin index="108" start="0.108" width="0.001" count="327" />
        <bin index="109" start="0.109" width="0.001" count="235" />
        <bin index="110" start="0.11" width="0.001" count="111" />
        <bin index="111" start="0.111" width="0.001" count="51" />
        <bin index="112" start="0.112" width="0.001" count="22" />
        <bin index="113" start="0.113" width="0.001" count="8" />
        <bin index="114" start="0.114" width="0.001" count="1" />
        <bin index="854" start="0.854" width="0.001" count="1" />
      </delayHistogram>
      <jitterHistogram nBins="850" >
        <bin index="0" start="0" width="0.001" count="9163" />
        <bin index="1" start="0.001" width="0.001" count="7800" />
        <bin index="2" start="0.002" width="0.001" count="369" />
        <bin index="3" start="0.003" width="0.001" count="60" />
        <bin index="4" start="0.004" width="0.001" count="81" />
        <bin index="5" start="0.005" width="0.001" count="110" />
        <bin index="6" start="0.006" width="0.001" count="80" />
        <bin index="7" start="0.007" width="0.001" count="57" />
        <bin index="8" start="0.008" width="0.001" count="13" />
        <bin index="9" start="0.009" width="0.001" count="4" />
        <bin index="10" start="0.01" width="0.001" count="2" />
        <bin index="12" start="0.012" width="0.001" count="1" />
        <bin index="13" start="0.013" width="0.001" count="2" />
        <bin index="14" start="0.014" width="0.001" count="2" />
        <bin index="15" start="0.015" width="0.001" count="2" />
        <bin index="16" start="0.016" width="0.001" count="1" />
        <bin index="17" start="0.017" width="0.001" count="5" />
        <bin index="18" start="0.018" width="0.001" count="1" />
        <bin index="19" start="0.019" width="0.001" count="4" />
        <bin index="22" start="0.022" width="0.001" count="2" />
        <bin index="26" start="0.026" width="0.001" count="2" />
        <bin index="27" start="0.027" width="0.001" count="4" />
        <bin index="28" start="0.028" width="0.001" count="2" />
        <bin index="29" start="0.029" width="0.001" count="3" />
        <bin index="30" start="0.03" width="0.001" count="2" />
        <bin index="31" start="0.031" width="0.001" count="3" />
        <bin index="32" start="0.032" width="0.001" count="3" />
        <bin index="33" start="0.033" width="0.001" count="5" />
        <bin index="34" start="0.034" width="0.001" count="4" />
        <bin index="35" start="0.035" width="0.001" count="5" />
        <bin index="36" start="0.036" width="0.001" count="3" />
        <bin index="37" start="0.037" width="0.001" count="9" />
        <bin index="38" start="0.038" width="0.001" count="7" />
        <bin index="39" start="0.039" width="0.001" count="7" />
        <bin index="40" start="0.04" width="0.001" count="2" />
        <bin index="41" start="0.041" width="0.001" count="4" />
        <bin index="42" start="0.042" width="0.001" count="8" />
        <bin index="43" start="0.043" width="0.001" count="3" />
        <bin index="44" start="0.044" width="0.001" count="1" />
        <bin index="45" start="0.045" width="0.001" count="6" />
        <bin index="46" start="0.046" width="0.001" count="1" />
        <bin index="47" start="0.047" width="0.001" count="1" />
        <bin index="48" start="0.048" width="0.001" count="2" />
        <bin index="49" start="0.049" width="0.001" count="4" />
        <bin index="50" start="0.05" width="0.001" count="3" />
        <bin index="51" start="0.051" width="0.001" count="5" />
        <bin index="52" start="0.052" width="0.001" count="3" />
        <bin index="53" start="0.053" width="0.001" count="2" />
        <bin index="54" start="0.054" width="0.001" count="9" />
        <bin index="55" start="0.055" width="0.001" count="5" />
        <bin index="56" start="0.056" width="0.001" count="8" />
        <bin index="57" start="0.057" width="0.001" count="6" />
        <bin index="58" start="0.058" width="0.001" count="3" />
        <bin index="59" start="0.059" width="0.001" count="5" />
        <bin index="60" start="0.06" width="0.001" count="3" />
        <bin index="61" start="0.061" width="0.001" count="6" />
        <bin index="62" start="0.062" width="0.001" count="6" />
        <bin index="63" start="0.063" width="0.001" count="9" />
        <bin index="64" start="0.064" width="0.001" count="4" />
        <bin index="65" start="0.065" width="0.001" count="11" />
        <bin index="66" start="0.066" width="0.001" count="7" />
        <bin index="67" start="0.067" width="0.001" count="11" />
        <bin index="68" start="0.068" width="0.001" count="10" />
        <bin index="69" start="0.069" width="0.001" count="3" />
        <bin index="70" start="0.07" width="0.001" count="12" />
        <bin index="71" start="0.071" width="0.001" count="9" />
        <bin index="72" start="0.072" width="0.001" count="7" />
        <bin index="73" start="0.073" width="0.001" count="16" />
        <bin index="74" start="0.074" width="0.001" count="10" />
        <bin index="75" start="0.075" width="0.001" count="5" />
        <bin index="76" start="0.076" width="0.001" count="14" />
        <bin index="77" start="0.077" width="0.001" count="13" />
        <bin index="78" start="0.078" width="0.001" count="13" />
        <bin index="79" start="0.079" width="0.001" count="13" />
        <bin index="80" start="0.08" width="0.001" count="15" />
        <bin index="81" start="0.081" width="0.001" count="12" />
        <bin index="82" start="0.082" width="0.001" count="16" />
        <bin index="83" start="0.083" width="0.001" count="15" />
        <bin index="84" start="0.084" width="0.001" count="16" />
        <bin index="85" start="0.085" width="0.001" count="14" />
        <bin index="86" start="0.086" width="0.001" count="16" />
        <bin index="87" start="0.087" width="0.001" count="12" />
        <bin index="88" start="0.088" width="0.001" count="16" />
        <bin index="89" start="0.089" width="0.001" count="17" />
        <bin index="90" start="0.09" width="0.001" count="12" />
        <bin index="91" start="0.091" width="0.001" count="19" />
        <bin index="92" start="0.092" width="0.001" count="12" />
        <bin index="93" start="0.093" width="0.001" count="17" />
        <bin index="94" start="0.094" width="0.001" count="18" />
        <bin index="95" start="0.095" width="0.001" count="16" />
        <bin index="96" start="0.096" width="0.001" count="10" />
        <bin index="97" start="0.097" width="0.001" count="11" />
        <bin index="98" start="0.098" width="0.001" count="1" />
        <bin index="99" start="0.099" width="0.001" count="11" />
        <bin index="100" start="0.1" width="0.001" count="4" />
        <bin index="101" start="0.101" width="0.001" count="6" />
        <bin index="102" start="0.102" width="0.001" count="4" />
        <bin index="103" start="0.103" width="0.001" count="1" />
        <bin index="104" start="0.104" width="0.001" count="4" />
        <bin index="106" start="0.106" width="0.001" count="1" />
        <bin index="748" start="0.748" width="0.001" count="1" />
        <bin index="849" start="0.849" width="0.001" count="1" />
      </jitterHistogram>
      <packetSizeHistogram nBins="30" >
        <bin index="2" start="40" width="20" count="1" />
        <bin index="4" start="80" width="20" count="1" />
        <bin index="11" start="220" width="20" count="1" />
        <bin index="16" start="320" width="20" count="1" />
        <bin index="18" start="360" width="20" count="1" />
        <bin index="19" start="380" width="20" count="1" />
        <bin index="20" start="400" width="20" count="1" />
        <bin index="23" start="460" width="20" count="1" />
        <bin index="29" start="580" width="20" count="18372" />
      </packetSizeHistogram>
      <flowInterruptionsHistogram nBins="4" >
        <bin index="3" start="0.75" width="0.25" count="1" />
      </flowInterruptionsHistogram>
    </Flow>
    <Flow flowId="10" timeFirstTxPacket="+3013938004.0ns" timeFirstRxPacket="+3018999999.0ns" timeLastTxPacket="+59956945996.0ns" timeLastRxPacket="+59946531000.0ns" delaySum="+2983596713168.0ns" jitterSum="+63998746654.0ns" lastDelay="+17597961.0ns" txBytes="19336942" rxBytes="19291026" txPackets="32892" rxPackets="32813" lostPackets="16" timesForwarded="32813">
      <delayHistogram nBins="253" >
        <bin index="3" start="0.003" width="0.001" count="1" />
        <bin index="4" start="0.004" width="0.001" count="1" />
        <bin index="5" start="0.005" width="0.001" count="38" />
        <bin index="6" start="0.006" width="0.001" count="23" />
        <bin index="7" start="0.007" width="0.001" count="16" />
        <bin index="8" start="0.008" width="0.001" count="19" />
        <bin index="9" start="0.009" width="0.001" count="13" />
        <bin index="10" start="0.01" width="0.001" count="12" />
        <bin index="11" start="0.011" width="0.001" count="14" />
        <bin index="12" start="0.012" width="0.001" count="14" />
        <bin index="13" start="0.013" width="0.001" count="15" />
        <bin index="14" start="0.014" width="0.001" count="14" />
        <bin index="15" start="0.015" width="0.001" count="10" />
        <bin index="16" start="0.016" width="0.001" count="17" />
        <bin index="17" start="0.017" width="0.001" count="14" />
        <bin index="18" start="0.018" width="0.001" count="10" />
        <bin index="19" start="0.019" width="0.001" count="7" />
        <bin index="20" start="0.02" width="0.001" count="13" />
        <bin index="21" start="0.021" width="0.001" count="7" />
        <bin index="22" start="0.022" width="0.001" count="8" />
        <bin index="23" start="0.023" width="0.001" count="10" />
        <bin index="24" start="0.024" width="0.001" count="8" />
        <bin index="25" start="0.025" width="0.001" count="6" />
        <bin index="26" start="0.026" width="0.001" count="6" />
        <bin index="27" start="0.027" width="0.001" count="4" />
        <bin index="28" start="0.028" width="0.001" count="8" />
        <bin index="29" start="0.029" width="0.001" count="7" />
        <bin index="30" start="0.03" width="0.001" count="8" />
        <bin index="31" start="0.031" width="0.001" count="9" />
        <bin index="32" start="0.032" width="0.001" count="5" />
        <bin index="33" start="0.033" width="0.001" count="2" />
        <bin index="34" start="0.034" width="0.001" count="2" />
        <bin index="35" start="0.035" width="0.001" count="2" />
        <bin index="36" start="0.036" width="0.001" count="1" />
        <bin index="37" start="0.037" width="0.001" count="6" />
        <bin index="38" start="0.038" width="0.001" count="2" />
        <bin index="39" start="0.039" width="0.001" count="6" />
        <bin index="40" start="0.04" width="0.001" count="3" />
        <bin index="41" start="0.041" width="0.001" count="4" />
        <bin index="42" start="0.042" width="0.001" count="3" />
        <bin index="43" start="0.043" width="0.001" count="5" />
        <bin index="44" start="0.044" width="0.001" count="3" />
        <bin index="45" start="0.045" width="0.001" count="3" />
        <bin index="46" start="0.046" width="0.001" count="4" />
        <bin index="47" start="0.047" width="0.001" count="4" />
        <bin index="48" start="0.048" width="0.001" count="2" />
        <bin index="49" start="0.049" width="0.001" count="6" />
        <bin index="50" start="0.05" width="0.001" count="9" />
        <bin index="51" start="0.051" width="0.001" count="17" />
        <bin index="52" start="0.052" width="0.001" count="15" />
        <bin index="53" start="0.053" width="0.001" count="17" />
        <bin index="54" start="0.054" width="0.001" count="18" />
        <bin index="55" start="0.055" width="0.001" count="27" />
        <bin index="56" start="0.056" width="0.001" count="50" />
        <bin index="57" start="0.057" width="0.001" count="78" />
        <bin index="58" start="0.058" width="0.001" count="103" />
        <bin index="59" start="0.059" width="0.001" count="116" />
        <bin index="60" start="0.06" width="0.001" count="125" />
        <bin index="61" start="0.061" width="0.001" count="139" />
        <bin index="62" start="0.062" width="0.001" count="139" />
        <bin index="63" start="0.063" width="0.001" count="207" />
        <bin index="64" start="0.064" width="0.001" count="253" />
        <bin index="65" start="0.065" width="0.001" count="244" />
        <bin index="66" start="0.066" width="0.001" count="264" />
        <bin index="67" start="0.067" width="0.001" count="322" />
        <bin index="68" start="0.068" width="0.001" count="315" />
        <bin index="69" start="0.069" width="0.001" count="238" />
        <bin index="70" start="0.07" width="0.001" count="205" />
        <bin index="71" start="0.071" width="0.001" count="216" />
        <bin index="72" start="0.072" width="0.001" count="352" />
        <bin index="73" start="0.073" width="0.001" count="316" />
        <bin index="74" start="0.074" width="0.001" count="295" />
        <bin index="75" start="0.075" width="0.001" count="332" />
        <bin index="76" start="0.076" width="0.001" count="503" />
        <bin index="77" start="0.077" width="0.001" count="510" />
        <bin index="78" start="0.078" width="0.001" count="487" />
        <bin index="79" start="0.079" width="0.001" count="539" />
        <bin index="80" start="0.08" width="0.001" count="529" />
        <bin index="81" start="0.081" width="0.001" count="606" />
        <bin index="82" start="0.082" width="0.001" count="590" />
        <bin index="83" start="0.083" width="0.001" count="612" />
        <bin index="84" start="0.084" width="0.001" count="625" />
        <bin index="85" start="0.085" width="0.001" count="674" />
        <bin index="86" start="0.086" width="0.001" count="621" />
        <bin index="87" start="0.087" width="0.001" count="680" />
        <bin index="88" start="0.088" width="0.001" count="752" />
        <bin index="89" start="0.089" width="0.001" count="852" />
        <bin index="90" start="0.09" width="0.001" count="962" />
        <bin index="91" start="0.091" width="0.001" count="833" />
        <bin index="92" start="0.092" width="0.001" count="859" />
        <bin index="93" start="0.093" width="0.001" count="984" />
        <bin index="94" start="0.094" width="0.001" count="1212" />
        <bin index="95" start="0.095" width="0.001" count="1118" />
        <bin index="96" start="0.096" width="0.001" count="924" />
        <bin index="97" start="0.097" width="0.001" count="1096" />
        <bin index="98" start="0.098" width="0.001" count="1173" />
        <bin index="99" start="0.099" width="0.001" count="1170" />
        <bin index="100" start="0.1" width="0.001" count="1014" />
        <bin index="101" start="0.101" width="0.001" count="932" />
        <bin index="102" start="0.102" width="0.001" count="1153" />
        <bin index="103" start="0.103" width="0.001" count="1236" />
        <bin index="104" start="0.104" width="0.001" count="972" />
        <bin index="105" start="0.105" width="0.001" count="853" />
        <bin index="106" start="0.106" width="0.001" count="701" />
        <bin index="107" start="0.107" width="0.001" count="789" />
        <bin index="108" start="0.108" width="0.001" count="513" />
        <bin index="109" start="0.109" width="0.001" count="291" />
        <bin index="110" start="0.11" width="0.001" count="202" />
        <bin index="111" start="0.111" width="0.001" count="57" />
        <bin index="112" start="0.112" width="0.001" count="25" />
        <bin index="113" start="0.113" width="0.001" count="8" />
        <bin index="114" start="0.114" width="0.001" count="6" />
        <bin index="125" start="0.125" width="0.001" count="4" />
        <bin index="126" start="0.126" width="0.001" count="10" />
        <bin index="127" start="0.127" width="0.001" count="10" />
        <bin index="128" start="0.128" width="0.001" count="21" />
        <bin index="129" start="0.129" width="0.001" count="48" />
        <bin index="130" start="0.13" width="0.001" count="4" />
        <bin index="131" start="0.131" width="0.001" count="2" />
        <bin index="132" start="0.132" width="0.001" count="3" />
        <bin index="133" start="0.133" width="0.001" count="2" />
        <bin index="146" start="0.146" width="0.001" count="2" />
        <bin index="147" start="0.147" width="0.001" count="2" />
        <bin index="148" start="0.148" width="0.001" count="2" />
        <bin index="149" start="0.149" width="0.001" count="2" />
        <bin index="150" start="0.15" width="0.001" count="2" />
        <bin index="151" start="0.151" width="0.001" count="2" />
        <bin index="152" start="0.152" width="0.001" count="2" />
        <bin index="153" start="0.153" width="0.001" count="2" />
        <bin index="154" start="0.154" width="0.001" count="2" />
        <bin index="155" start="0.155" width="0.001" count="2" />
        <bin index="156" start="0.156" width="0.001" count="2" />
        <bin index="157" start="0.157" width="0.001" count="2" />
        <bin index="158" start="0.158" width="0.001" count="12" />
        <bin index="159" start="0.159" width="0.001" count="8" />
        <bin index="160" start="0.16" width="0.001" count="4" />
        <bin index="161" start="0.161" width="0.001" count="3" />
        <bin index="162" start="0.162" width="0.001" count="6" />
        <bin index="163" start="0.163" width="0.001" count="8" />
        <bin index="164" start="0.164" width="0.001" count="5" />
        <bin index="165" start="0.165" width="0.001" count="6" />
        <bin index="166" start="0.166" width="0.001" count="4" />
        <bin index="167" start="0.167" width="0.001" count="6" />
        <bin index="168" start="0.168" width="0.001" count="11" />
        <bin index="169" start="0.169" width="0.001" count="6" />
        <bin index="170" start="0.17" width="0.001" count="4" />
        <bin index="171" start="0.171" width="0.001" count="2" />
        <bin index="172" start="0.172" width="0.001" count="2" />
        <bin index="173" start="0.173" width="0.001" count="3" />
        <bin index="174" start="0.174" width="0.001" count="7" />
        <bin index="175" start="0.175" width="0.001" count="4" />
        <bin index="225" start="0.225" width="0.001" count="2" />
        <bin index="226" start="0.226" width="0.001" count="1" />
        <bin index="227" start="0.227" width="0.001" count="2" />
        <bin index="229" start="0.229" width="0.001" count="2" />
        <bin index="230" start="0.23" width="0.001" count="2" />
        <bin index="231" start="0.231" width="0.001" count="2" />
        <bin index="232" start="0.232" width="0.001" count="3" />
        <bin index="233" start="0.233" width="0.001" count="4" />
        <bin index="234" start="0.234" width="0.001" count="4" />
        <bin index="235" start="0.235" width="0.001" count="6" />
        <bin index="236" start="0.236" width="0.001" count="1" />
        <bin index="237" start="0.237" width="0.001" count="10" />
        <bin index="238" start="0.238" width="0.001" count="10" />
        <bin index="239" start="0.239" width="0.001" count="3" />
        <bin index="240" start="0.24" width="0.001" count="7" />
        <bin index="241" start="0.241" width="0.001" count="4" />
        <bin index="242" start="0.242" width="0.001" count="5" />
        <bin index="243" start="0.243" width="0.001" count="7" />
        <bin index="244" start="0.244" width="0.001" count="3" />
        <bin index="245" start="0.245" width="0.001" count="9" />
        <bin index="246" start="0.246" width="0.001" count="9" />
        <bin index="247" start="0.247" width="0.001" count="3" />
        <bin index="248" start="0.248" width="0.001" count="2" />
        <bin index="249" start="0.249" width="0.001" count="2" />
        <bin index="250" start="0.25" width="0.001" count="3" />
        <bin index="251" start="0.251" width="0.001" count="6" />
        <bin index="252" start="0.252" width="0.001" count="2" />
      </delayHistogram>
      <jitterHistogram nBins="216" >
        <bin index="0" start="0" width="0.001" count="16489" />
        <bin index="1" start="0.001" width="0.001" count="14071" />
        <bin index="2" start="0.002" width="0.001" count="798" />
        <bin index="3" start="0.003" width="0.001" count="202" />
        <bin index="4" start="0.004" width="0.001" count="238" />
        <bin index="5" start="0.005" width="0.001" count="175" />
        <bin index="6" start="0.006" width="0.001" count="106" />
        <bin index="7" start="0.007" width="0.001" count="66" />
        <bin index="8" start="0.008" width="0.001" count="11" />
        <bin index="9" start="0.009" width="0.001" count="2" />
        <bin index="10" start="0.01" width="0.001" count="2" />
        <bin index="11" start="0.011" width="0.001" count="3" />
        <bin index="12" start="0.012" width="0.001" count="2" />
        <bin index="13" start="0.013" width="0.001" count="4" />
        <bin index="14" start="0.014" width="0.001" count="4" />
        <bin index="15" start="0.015" width="0.001" count="5" />
        <bin index="16" start="0.016" width="0.001" count="2" />
        <bin index="17" start="0.017" width="0.001" count="6" />
        <bin index="18" start="0.018" width="0.001" count="4" />
        <bin index="19" start="0.019" width="0.001" count="3" />
        <bin index="20" start="0.02" width="0.001" count="4" />
        <bin index="22" start="0.022" width="0.001" count="4" />
        <bin index="23" start="0.023" width="0.001" count="9" />
        <bin index="24" start="0.024" width="0.001" count="6" />
        <bin index="25" start="0.025" width="0.001" count="3" />
        <bin index="26" start="0.026" width="0.001" count="4" />
        <bin index="27" start="0.027" width="0.001" count="4" />
        <bin index="28" start="0.028" width="0.001" count="2" />
        <bin index="29" start="0.029" width="0.001" count="4" />
        <bin index="30" start="0.03" width="0.001" count="3" />
        <bin index="31" start="0.031" width="0.001" count="2" />
        <bin index="32" start="0.032" width="0.001" count="1" />
        <bin index="33" start="0.033" width="0.001" count="5" />
        <bin index="35" start="0.035" width="0.001" count="1" />
        <bin index="37" start="0.037" width="0.001" count="1" />
        <bin index="39" start="0.039" width="0.001" count="1" />
        <bin index="41" start="0.041" width="0.001" count="2" />
        <bin index="42" start="0.042" width="0.001" count="2" />
        <bin index="43" start="0.043" width="0.001" count="1" />
        <bin index="44" start="0.044" width="0.001" count="5" />
        <bin index="45" start="0.045" width="0.001" count="3" />
        <bin index="46" start="0.046" width="0.001" count="8" />
        <bin index="47" start="0.047" width="0.001" count="4" />
        <bin index="48" start="0.048" width="0.001" count="6" />
        <bin index="49" start="0.049" width="0.001" count="12" />
        <bin index="50" start="0.05" width="0.001" count="12" />
        <bin index="51" start="0.051" width="0.001" count="4" />
        <bin index="52" start="0.052" width="0.001" count="13" />
        <bin index="53" start="0.053" width="0.001" count="16" />
        <bin index="54" start="0.054" width="0.001" count="13" />
        <bin index="55" start="0.055" width="0.001" count="9" />
        <bin index="56" start="0.056" width="0.001" count="18" />
        <bin index="57" start="0.057" width="0.001" count="18" />
        <bin index="58" start="0.058" width="0.001" count="14" />
        <bin index="59" start="0.059" width="0.001" count="11" />
        <bin index="60" start="0.06" width="0.001" count="12" />
        <bin index="61" start="0.061" width="0.001" count="11" />
        <bin index="62" start="0.062" width="0.001" count="14" />
        <bin index="63" start="0.063" width="0.001" count="11" />
        <bin index="64" start="0.064" width="0.001" count="19" />
        <bin index="65" start="0.065" width="0.001" count="10" />
        <bin index="66" start="0.066" width="0.001" count="10" />
        <bin index="67" start="0.067" width="0.001" count="15" />
        <bin index="68" start="0.068" width="0.001" count="9" />
        <bin index="69" start="0.069" width="0.001" count="9" />
        <bin index="70" start="0.07" width="0.001" count="21" />
        <bin index="71" start="0.071" width="0.001" count="16" />
        <bin index="72" start="0.072" width="0.001" count="13" />
        <bin index="73" start="0.073" width="0.001" count="6" />
        <bin index="74" start="0.074" width="0.001" count="16" />
        <bin index="75" start="0.075" width="0.001" count="13" />
        <bin index="76" start="0.076" width="0.001" count="11" />
        <bin index="77" start="0.077" width="0.001" count="13" />
        <bin index="78" start="0.078" width="0.001" count="13" />
        <bin index="79" start="0.079" width="0.001" count="8" />
        <bin index="80" start="0.08" width="0.001" count="8" />
        <bin index="81" start="0.081" width="0.001" count="18" />
        <bin index="82" start="0.082" width="0.001" count="11" />
        <bin index="83" start="0.083" width="0.001" count="9" />
        <bin index="84" start="0.084" width="0.001" count="10" />
        <bin index="85" start="0.085" width="0.001" count="9" />
        <bin index="86" start="0.086" width="0.001" count="6" />
        <bin index="87" start="0.087" width="0.001" count="7" />
        <bin index="88" start="0.088" width="0.001" count="8" />
        <bin index="89" start="0.089" width="0.001" count="6" />
        <bin index="90" start="0.09" width="0.001" count="7" />
        <bin index="91" start="0.091" width="0.001" count="8" />
        <bin index="92" start="0.092" width="0.001" count="6" />
        <bin index="93" start="0.093" width="0.001" count="1" />
        <bin index="94" start="0.094" width="0.001" count="5" />
        <bin index="95" start="0.095" width="0.001" count="8" />
        <bin index="96" start="0.096" width="0.001" count="2" />
        <bin index="97" start="0.097" width="0.001" count="1" />
        <bin index="98" start="0.098" width="0.001" count="4" />
        <bin index="99" start="0.099" width="0.001" count="1" />
        <bin index="100" start="0.1" width="0.001" count="5" />
        <bin index="101" start="0.101" width="0.001" count="2" />
        <bin index="102" start="0.102" width="0.001" count="1" />
        <bin index="215" start="0.215" width="0.001" count="1" />
      </jitterHistogram>
      <packetSizeHistogram nBins="30" >
        <bin index="2" start="40" width="20" count="1" />
        <bin index="4" start="80" width="20" count="1" />
        <bin index="7" start="140" width="20" count="2" />
        <bin index="11" start="220" width="20" count="1" />
        <bin index="16" start="320" width="20" count="1" />
        <bin index="17" start="340" width="20" count="2" />
        <bin index="29" start="580" width="20" count="32805" />
      </packetSizeHistogram>
      <flowInterruptionsHistogram nBins="0" >
      </flowInterruptionsHistogram>
    </Flow>
    <Flow flowId="11" timeFirstTxPacket="+3013942643.0ns" timeFirstRxPacket="+3018999999.0ns" timeLastTxPacket="+59999933039.0ns" timeLastRxPacket="+59999799000.0ns" delaySum="+2378370809866.0ns" jitterSum="+62309181139.0ns" lastDelay="+37865961.0ns" txBytes="15326299" rxBytes="15305079" txPackets="26070" rxPackets="26033" lostPackets="17" timesForwarded="26033">
      <delayHistogram nBins="235" >
        <bin index="3" start="0.003" width="0.001" count="3" />
        <bin index="5" start="0.005" width="0.001" count="91" />
        <bin index="6" start="0.006" width="0.001" count="40" />
        <bin index="7" start="0.007" width="0.001" count="16" />
        <bin index="8" start="0.008" width="0.001" count="13" />
        <bin index="9" start="0.009" width="0.001" count="12" />
        <bin index="10" start="0.01" width="0.001" count="14" />
        <bin index="11" start="0.011" width="0.001" count="9" />
        <bin index="12" start="0.012" width="0.001" count="15" />
        <bin index="13" start="0.013" width="0.001" count="12" />
        <bin index="14" start="0.014" width="0.001" count="12" />
        <bin index="15" start="0.015" width="0.001" count="9" />
        <bin index="16" start="0.016" width="0.001" count="10" />
        <bin index="17" start="0.017" width="0.001" count="8" />
        <bin index="18" start="0.018" width="0.001" count="7" />
        <bin index="19" start="0.019" width="0.001" count="10" />
        <bin index="20" start="0.02" width="0.001" count="8" />
        <bin index="21" start="0.021" width="0.001" count="8" />
        <bin index="22" start="0.022" width="0.001" count="7" />
        <bin index="23" start="0.023" width="0.001" count="5" />
        <bin index="24" start="0.024" width="0.001" count="3" />
        <bin index="25" start="0.025" width="0.001" count="6" />
        <bin index="26" start="0.026" width="0.001" count="7" />
        <bin index="27" start="0.027" width="0.001" count="3" />
        <bin index="28" start="0.028" width="0.001" count="3" />
        <bin index="29" start="0.029" width="0.001" count="5" />
        <bin index="30" start="0.03" width="0.001" count="3" />
        <bin index="31" start="0.031" width="0.001" count="3" />
        <bin index="32" start="0.032" width="0.001" count="8" />
        <bin index="33" start="0.033" width="0.001" count="5" />
        <bin index="34" start="0.034" width="0.001" count="4" />
        <bin index="35" start="0.035" width="0.001" count="4" />
        <bin index="36" start="0.036" width="0.001" count="4" />
        <bin index="37" start="0.037" width="0.001" count="7" />
        <bin index="38" start="0.038" width="0.001" count="4" />
        <bin index="39" start="0.039" width="0.001" count="8" />
        <bin index="40" start="0.04" width="0.001" count="5" />
        <bin index="41" start="0.041" width="0.001" count="5" />
        <bin index="42" start="0.042" width="0.001" count="5" />
        <bin index="43" start="0.043" width="0.001" count="9" />
        <bin index="44" start="0.044" width="0.001" count="13" />
        <bin index="45" start="0.045" width="0.001" count="5" />
        <bin index="46" start="0.046" width="0.001" count="3" />
        <bin index="47" start="0.047" width="0.001" count="2" />
        <bin index="48" start="0.048" width="0.001" count="6" />
        <bin index="49" start="0.049" width="0.001" count="6" />
        <bin index="50" start="0.05" width="0.001" count="8" />
        <bin index="51" start="0.051" width="0.001" count="13" />
        <bin index="52" start="0.052" width="0.001" count="15" />
        <bin index="53" start="0.053" width="0.001" count="21" />
        <bin index="54" start="0.054" width="0.001" count="26" />
        <bin index="55" start="0.055" width="0.001" count="34" />
        <bin index="56" start="0.056" width="0.001" count="50" />
        <bin index="57" start="0.057" width="0.001" count="67" />
        <bin index="58" start="0.058" width="0.001" count="113" />
        <bin index="59" start="0.059" width="0.001" count="115" />
        <bin index="60" start="0.06" width="0.001" count="95" />
        <bin index="61" start="0.061" width="0.001" count="134" />
        <bin index="62" start="0.062" width="0.001" count="120" />
        <bin index="63" start="0.063" width="0.001" count="153" />
        <bin index="64" start="0.064" width="0.001" count="180" />
        <bin index="65" start="0.065" width="0.001" count="214" />
        <bin index="66" start="0.066" width="0.001" count="171" />
        <bin index="67" start="0.067" width="0.001" count="212" />
        <bin index="68" start="0.068" width="0.001" count="217" />
        <bin index="69" start="0.069" width="0.001" count="230" />
        <bin index="70" start="0.07" width="0.001" count="183" />
        <bin index="71" start="0.071" width="0.001" count="197" />
        <bin index="72" start="0.072" width="0.001" count="197" />
        <bin index="73" start="0.073" width="0.001" count="216" />
        <bin index="74" start="0.074" width="0.001" count="280" />
        <bin index="75" start="0.075" width="0.001" count="316" />
        <bin index="76" start="0.076" width="0.001" count="324" />
        <bin index="77" start="0.077" width="0.001" count="377" />
        <bin index="78" start="0.078" width="0.001" count="376" />
        <bin index="79" start="0.079" width="0.001" count="367" />
        <bin index="80" start="0.08" width="0.001" count="411" />
        <bin index="81" start="0.081" width="0.001" count="392" />
        <bin index="82" start="0.082" width="0.001" count="461" />
        <bin index="83" start="0.083" width="0.001" count="465" />
        <bin index="84" start="0.084" width="0.001" count="489" />
        <bin index="85" start="0.085" width="0.001" count="449" />
        <bin index="86" start="0.086" width="0.001" count="421" />
        <bin index="87" start="0.087" width="0.001" count="447" />
        <bin index="88" start="0.088" width="0.001" count="530" />
        <bin index="89" start="0.089" width="0.001" count="666" />
        <bin index="90" start="0.09" width="0.001" count="717" />
        <bin index="91" start="0.091" width="0.001" count="706" />
        <bin index="92" start="0.092" width="0.001" count="739" />
        <bin index="93" start="0.093" width="0.001" count="857" />
        <bin index="94" start="0.094" width="0.001" count="826" />
        <bin index="95" start="0.095" width="0.001" count="825" />
        <bin index="96" start="0.096" width="0.001" count="794" />
        <bin index="97" start="0.097" width="0.001" count="809" />
        <bin index="98" start="0.098" width="0.001" count="963" />
        <bin index="99" start="0.099" width="0.001" count="903" />
        <bin index="100" start="0.1" width="0.001" count="767" />
        <bin index="101" start="0.101" width="0.001" count="812" />
        <bin index="102" start="0.102" width="0.001" count="854" />
        <bin index="103" start="0.103" width="0.001" count="903" />
        <bin index="104" start="0.104" width="0.001" count="808" />
        <bin index="105" start="0.105" width="0.001" count="711" />
        <bin index="106" start="0.106" width="0.001" count="687" />
        <bin index="107" start="0.107" width="0.001" count="612" />
        <bin index="108" start="0.108" width="0.001" count="433" />
        <bin index="109" start="0.109" width="0.001" count="277" />
        <bin index="110" start="0.11" width="0.001" count="217" />
        <bin index="111" start="0.111" width="0.001" count="99" />
        <bin index="112" start="0.112" width="0.001" count="21" />
        <bin index="113" start="0.113" width="0.001" count="6" />
        <bin index="114" start="0.114" width="0.001" count="1" />
        <bin index="122" start="0.122" width="0.001" count="2" />
        <bin index="123" start="0.123" width="0.001" count="4" />
        <bin index="124" start="0.124" width="0.001" count="4" />
        <bin index="125" start="0.125" width="0.001" count="4" />
        <bin index="126" start="0.126" width="0.001" count="2" />
        <bin index="127" start="0.127" width="0.001" count="4" />
        <bin index="128" start="0.128" width="0.001" count="4" />
        <bin index="129" start="0.129" width="0.001" count="5" />
        <bin index="130" start="0.13" width="0.001" count="4" />
        <bin index="131" start="0.131" width="0.001" count="6" />
        <bin index="132" start="0.132" width="0.001" count="10" />
        <bin index="133" start="0.133" width="0.001" count="9" />
        <bin index="134" start="0.134" width="0.001" count="4" />
        <bin index="135" start="0.135" width="0.001" count="5" />
        <bin index="136" start="0.136" width="0.001" count="13" />
        <bin index="137" start="0.137" width="0.001" count="10" />
        <bin index="138" start="0.138" width="0.001" count="4" />
        <bin index="139" start="0.139" width="0.001" count="4" />
        <bin index="140" start="0.14" width="0.001" count="4" />
        <bin index="141" start="0.141" width="0.001" count="8" />
        <bin index="142" start="0.142" width="0.001" count="3" />
        <bin index="143" start="0.143" width="0.001" count="11" />
        <bin index="144" start="0.144" width="0.001" count="19" />
        <bin index="145" start="0.145" width="0.001" count="18" />
        <bin index="146" start="0.146" width="0.001" count="13" />
        <bin index="147" start="0.147" width="0.001" count="50" />
        <bin index="148" start="0.148" width="0.001" count="53" />
        <bin index="149" start="0.149" width="0.001" count="19" />
        <bin index="150" start="0.15" width="0.001" count="5" />
        <bin index="151" start="0.151" width="0.001" count="6" />
        <bin index="152" start="0.152" width="0.001" count="5" />
        <bin index="195" start="0.195" width="0.001" count="2" />
        <bin index="196" start="0.196" width="0.001" count="2" />
        <bin index="197" start="0.197" width="0.001" count="2" />
        <bin index="198" start="0.198" width="0.001" count="2" />
        <bin index="199" start="0.199" width="0.001" count="2" />
        <bin index="200" start="0.2" width="0.001" count="2" />
        <bin index="201" start="0.201" width="0.001" count="3" />
        <bin index="202" start="0.202" width="0.001" count="4" />
        <bin index="203" start="0.203" width="0.001" count="4" />
        <bin index="204" start="0.204" width="0.001" count="1" />
        <bin index="205" start="0.205" width="0.001" count="5" />
        <bin index="206" start="0.206" width="0.001" count="8" />
        <bin index="207" start="0.207" width="0.001" count="6" />
        <bin index="208" start="0.208" width="0.001" count="6" />
        <bin index="209" start="0.209" width="0.001" count="9" />
        <bin index="210" start="0.21" width="0.001" count="6" />
        <bin index="211" start="0.211" width="0.001" count="2" />
        <bin index="212" start="0.212" width="0.001" count="2" />
        <bin index="213" start="0.213" width="0.001" count="3" />
        <bin index="214" start="0.214" width="0.001" count="6" />
        <bin index="215" start="0.215" width="0.001" count="7" />
        <bin index="216" start="0.216" width="0.001" count="8" />
        <bin index="217" start="0.217" width="0.001" count="8" />
        <bin index="218" start="0.218" width="0.001" count="3" />
        <bin index="219" start="0.219" width="0.001" count="5" />
        <bin index="220" start="0.22" width="0.001" count="6" />
        <bin index="221" start="0.221" width="0.001" count="11" />
        <bin index="222" start="0.222" width="0.001" count="3" />
        <bin index="223" start="0.223" width="0.001" count="3" />
        <bin index="224" start="0.224" width="0.001" count="2" />
        <bin index="225" start="0.225" width="0.001" count="3" />
        <bin index="226" start="0.226" width="0.001" count="6" />
        <bin index="227" start="0.227" width="0.001" count="7" />
        <bin index="228" start="0.228" width="0.001" count="9" />
        <bin index="229" start="0.229" width="0.001" count="5" />
        <bin index="230" start="0.23" width="0.001" count="3" />
        <bin index="231" start="0.231" width="0.001" count="4" />
        <bin index="232" start="0.232" width="0.001" count="4" />
        <bin index="233" start="0.233" width="0.001" count="2" />
        <bin index="234" start="0.234" width="0.001" count="1" />
      </delayHistogram>
      <jitterHistogram nBins="113" >
        <bin index="0" start="0" width="0.001" count="13142" />
        <bin index="1" start="0.001" width="0.001" count="11017" />
        <bin index="2" start="0.002" width="0.001" count="638" />
        <bin index="3" start="0.003" width="0.001" count="121" />
        <bin index="4" start="0.004" width="0.001" count="141" />
        <bin index="5" start="0.005" width="0.001" count="113" />
        <bin index="6" start="0.006" width="0.001" count="107" />
        <bin index="7" start="0.007" width="0.001" count="56" />
        <bin index="8" start="0.008" width="0.001" count="16" />
        <bin index="9" start="0.009" width="0.001" count="1" />
        <bin index="10" start="0.01" width="0.001" count="3" />
        <bin index="11" start="0.011" width="0.001" count="1" />
        <bin index="13" start="0.013" width="0.001" count="1" />
        <bin index="14" start="0.014" width="0.001" count="1" />
        <bin index="15" start="0.015" width="0.001" count="4" />
        <bin index="16" start="0.016" width="0.001" count="1" />
        <bin index="17" start="0.017" width="0.001" count="1" />
        <bin index="18" start="0.018" width="0.001" count="4" />
        <bin index="19" start="0.019" width="0.001" count="5" />
        <bin index="20" start="0.02" width="0.001" count="4" />
        <bin index="21" start="0.021" width="0.001" count="2" />
        <bin index="22" start="0.022" width="0.001" count="4" />
        <bin index="23" start="0.023" width="0.001" count="2" />
        <bin index="24" start="0.024" width="0.001" count="5" />
        <bin index="25" start="0.025" width="0.001" count="4" />
        <bin index="26" start="0.026" width="0.001" count="5" />
        <bin index="27" start="0.027" width="0.001" count="3" />
        <bin index="28" start="0.028" width="0.001" count="4" />
        <bin index="29" start="0.029" width="0.001" count="4" />
        <bin index="30" start="0.03" width="0.001" count="8" />
        <bin index="31" start="0.031" width="0.001" count="3" />
        <bin index="32" start="0.032" width="0.001" count="6" />
        <bin index="33" start="0.033" width="0.001" count="4" />
        <bin index="34" start="0.034" width="0.001" count="4" />
        <bin index="35" start="0.035" width="0.001" count="4" />
        <bin index="36" start="0.036" width="0.001" count="4" />
        <bin index="37" start="0.037" width="0.001" count="3" />
        <bin index="39" start="0.039" width="0.001" count="3" />
        <bin index="40" start="0.04" width="0.001" count="3" />
        <bin index="41" start="0.041" width="0.001" count="5" />
        <bin index="42" start="0.042" width="0.001" count="7" />
        <bin index="43" start="0.043" width="0.001" count="3" />
        <bin index="44" start="0.044" width="0.001" count="5" />
        <bin index="45" start="0.045" width="0.001" count="2" />
        <bin index="46" start="0.046" width="0.001" count="8" />
        <bin index="47" start="0.047" width="0.001" count="2" />
        <bin index="48" start="0.048" width="0.001" count="9" />
        <bin index="49" start="0.049" width="0.001" count="8" />
        <bin index="50" start="0.05" width="0.001" count="12" />
        <bin index="51" start="0.051" width="0.001" count="5" />
        <bin index="52" start="0.052" width="0.001" count="11" />
        <bin index="53" start="0.053" width="0.001" count="5" />
        <bin index="54" start="0.054" width="0.001" count="9" />
        <bin index="55" start="0.055" width="0.001" count="9" />
        <bin index="56" start="0.056" width="0.001" count="8" />
        <bin index="57" start="0.057" width="0.001" count="11" />
        <bin index="58" start="0.058" width="0.001" count="10" />
        <bin index="59" start="0.059" width="0.001" count="7" />
        <bin index="60" start="0.06" width="0.001" count="9" />
        <bin index="61" start="0.061" width="0.001" count="10" />
        <bin index="62" start="0.062" width="0.001" count="13" />
        <bin index="63" start="0.063" width="0.001" count="9" />
        <bin index="64" start="0.064" width="0.001" count="9" />
        <bin index="65" start="0.065" width="0.001" count="10" />
        <bin index="66" start="0.066" width="0.001" count="7" />
        <bin index="67" start="0.067" width="0.001" count="12" />
        <bin index="68" start="0.068" width="0.001" count="11" />
        <bin index="69" start="0.069" width="0.001" count="7" />
        <bin index="70" start="0.07" width="0.001" count="16" />
        <bin index="71" start="0.071" width="0.001" count="12" />
        <bin index="72" start="0.072" width="0.001" count="16" />
        <bin index="73" start="0.073" width="0.001" count="18" />
        <bin index="74" start="0.074" width="0.001" count="14" />
        <bin index="75" start="0.075" width="0.001" count="13" />
        <bin index="76" start="0.076" width="0.001" count="12" />
        <bin index="77" start="0.077" width="0.001" count="24" />
        <bin index="78" start="0.078" width="0.001" count="13" />
        <bin index="79" start="0.079" width="0.001" count="8" />
        <bin index="80" start="0.08" width="0.001" count="17" />
        <bin index="81" start="0.081" width="0.001" count="9" />
        <bin index="82" start="0.082" width="0.001" count="17" />
        <bin index="83" start="0.083" width="0.001" count="16" />
        <bin index="84" start="0.084" width="0.001" count="11" />
        <bin index="85" start="0.085" width="0.001" count="17" />
        <bin index="86" start="0.086" width="0.001" count="14" />
        <bin index="87" start="0.087" width="0.001" count="7" />
        <bin index="88" start="0.088" width="0.001" count="8" />
        <bin index="89" start="0.089" width="0.001" count="9" />
        <bin index="90" start="0.09" width="0.001" count="12" />
        <bin index="91" start="0.091" width="0.001" count="8" />
        <bin index="92" start="0.092" width="0.001" count="7" />
        <bin index="93" start="0.093" width="0.001" count="8" />
        <bin index="94" start="0.094" width="0.001" count="7" />
        <bin index="95" start="0.095" width="0.001" count="5" />
        <bin index="96" start="0.096" width="0.001" count="5" />
        <bin index="97" start="0.097" width="0.001" count="6" />
        <bin index="98" start="0.098" width="0.001" count="2" />
        <bin index="99" start="0.099" width="0.001" count="3" />
        <bin index="100" start="0.1" width="0.001" count="3" />
        <bin index="101" start="0.101" width="0.001" count="5" />
        <bin index="104" start="0.104" width="0.001" count="3" />
        <bin index="106" start="0.106" width="0.001" count="1" />
        <bin index="112" start="0.112" width="0.001" count="1" />
      </jitterHistogram>
      <packetSizeHistogram nBins="30" >
        <bin index="2" start="40" width="20" count="1" />
        <bin index="7" start="140" width="20" count="1" />
        <bin index="11" start="220" width="20" count="1" />
        <bin index="16" start="320" width="20" count="1" />
        <bin index="17" start="340" width="20" count="3" />
        <bin index="29" start="580" width="20" count="26026" />
      </packetSizeHistogram>
      <flowInterruptionsHistogram nBins="0" >
      </flowInterruptionsHistogram>
    </Flow>
    <Flow flowId="12" timeFirstTxPacket="+3013947282.0ns" timeFirstRxPacket="+3018999999.0ns" timeLastTxPacket="+59976933039.0ns" timeLastRxPacket="+59969325000.0ns" delaySum="+2416917440976.0ns" jitterSum="+64166857094.0ns" lastDelay="+75391961.0ns" txBytes="15613290" rxBytes="15577370" txPackets="26559" rxPackets="26497" lostPackets="20" timesForwarded="26497">
      <delayHistogram nBins="239" >
        <bin index="3" start="0.003" width="0.001" count="2" />
        <bin index="5" start="0.005" width="0.001" count="77" />
        <bin index="6" start="0.006" width="0.001" count="29" />
        <bin index="7" start="0.007" width="0.001" count="17" />
        <bin index="8" start="0.008" width="0.001" count="12" />
        <bin index="9" start="0.009" width="0.001" count="22" />
        <bin index="10" start="0.01" width="0.001" count="16" />
        <bin index="11" start="0.011" width="0.001" count="15" />
        <bin index="12" start="0.012" width="0.001" count="14" />
        <bin index="13" start="0.013" width="0.001" count="15" />
        <bin index="14" start="0.014" width="0.001" count="12" />
        <bin index="15" start="0.015" width="0.001" count="9" />
        <bin index="16" start="0.016" width="0.001" count="11" />
        <bin index="17" start="0.017" width="0.001" count="12" />
        <bin index="18" start="0.018" width="0.001" count="7" />
        <bin index="19" start="0.019" width="0.001" count="10" />
        <bin index="20" start="0.02" width="0.001" count="11" />
        <bin index="21" start="0.021" width="0.001" count="7" />
        <bin index="22" start="0.022" width="0.001" count="7" />
        <bin index="23" start="0.023" width="0.001" count="6" />
        <bin index="24" start="0.024" width="0.001" count="7" />
        <bin index="25" start="0.025" width="0.001" count="8" />
        <bin index="26" start="0.026" width="0.001" count="7" />
        <bin index="27" start="0.027" width="0.001" count="7" />
        <bin index="28" start="0.028" width="0.001" count="3" />
        <bin index="29" start="0.029" width="0.001" count="6" />
        <bin index="30" start="0.03" width="0.001" count="3" />
        <bin index="31" start="0.031" width="0.001" count="5" />
        <bin index="32" start="0.032" width="0.001" count="5" />
        <bin index="33" start="0.033" width="0.001" count="3" />
        <bin index="34" start="0.034" width="0.001" count="2" />
        <bin index="35" start="0.035" width="0.001" count="2" />
        <bin index="36" start="0.036" width="0.001" count="2" />
        <bin index="37" start="0.037" width="0.001" count="4" />
        <bin index="39" start="0.039" width="0.001" count="1" />
        <bin index="40" start="0.04" width="0.001" count="1" />
        <bin index="46" start="0.046" width="0.001" count="2" />
        <bin index="47" start="0.047" width="0.001" count="4" />
        <bin index="48" start="0.048" width="0.001" count="4" />
        <bin index="49" start="0.049" width="0.001" count="2" />
        <bin index="50" start="0.05" width="0.001" count="4" />
        <bin index="51" start="0.051" width="0.001" count="12" />
        <bin index="52" start="0.052" width="0.001" count="10" />
        <bin index="53" start="0.053" width="0.001" count="17" />
        <bin index="54" start="0.054" width="0.001" count="26" />
        <bin index="55" start="0.055" width="0.001" count="28" />
        <bin index="56" start="0.056" width="0.001" count="42" />
        <bin index="57" start="0.057" width="0.001" count="70" />
        <bin index="58" start="0.058" width="0.001" count="96" />
        <bin index="59" start="0.059" width="0.001" count="88" />
        <bin index="60" start="0.06" width="0.001" count="105" />
        <bin index="61" start="0.061" width="0.001" count="105" />
        <bin index="62" start="0.062" width="0.001" count="122" />
        <bin index="63" start="0.063" width="0.001" count="134" />
        <bin index="64" start="0.064" width="0.001" count="166" />
        <bin index="65" start="0.065" width="0.001" count="199" />
        <bin index="66" start="0.066" width="0.001" count="183" />
        <bin index="67" start="0.067" width="0.001" count="150" />
        <bin index="68" start="0.068" width="0.001" count="193" />
        <bin index="69" start="0.069" width="0.001" count="216" />
        <bin index="70" start="0.07" width="0.001" count="188" />
        <bin index="71" start="0.071" width="0.001" count="193" />
        <bin index="72" start="0.072" width="0.001" count="233" />
        <bin index="73" start="0.073" width="0.001" count="247" />
        <bin index="74" start="0.074" width="0.001" count="244" />
        <bin index="75" start="0.075" width="0.001" count="264" />
        <bin index="76" start="0.076" width="0.001" count="290" />
        <bin index="77" start="0.077" width="0.001" count="355" />
        <bin index="78" start="0.078" width="0.001" count="385" />
        <bin index="79" start="0.079" width="0.001" count="343" />
        <bin index="80" start="0.08" width="0.001" count="372" />
        <bin index="81" start="0.081" width="0.001" count="463" />
        <bin index="82" start="0.082" width="0.001" count="516" />
        <bin index="83" start="0.083" width="0.001" count="524" />
        <bin index="84" start="0.084" width="0.001" count="533" />
        <bin index="85" start="0.085" width="0.001" count="530" />
        <bin index="86" start="0.086" width="0.001" count="602" />
        <bin index="87" start="0.087" width="0.001" count="611" />
        <bin index="88" start="0.088" width="0.001" count="593" />
        <bin index="89" start="0.089" width="0.001" count="667" />
        <bin index="90" start="0.09" width="0.001" count="744" />
        <bin index="91" start="0.091" width="0.001" count="811" />
        <bin index="92" start="0.092" width="0.001" count="800" />
        <bin index="93" start="0.093" width="0.001" count="753" />
        <bin index="94" start="0.094" width="0.001" count="768" />
        <bin index="95" start="0.095" width="0.001" count="914" />
        <bin index="96" start="0.096" width="0.001" count="904" />
        <bin index="97" start="0.097" width="0.001" count="757" />
        <bin index="98" start="0.098" width="0.001" count="800" />
        <bin index="99" start="0.099" width="0.001" count="862" />
        <bin index="100" start="0.1" width="0.001" count="1017" />
        <bin index="101" start="0.101" width="0.001" count="820" />
        <bin index="102" start="0.102" width="0.001" count="777" />
        <bin index="103" start="0.103" width="0.001" count="934" />
        <bin index="104" start="0.104" width="0.001" count="899" />
        <bin index="105" start="0.105" width="0.001" count="779" />
        <bin index="106" start="0.106" width="0.001" count="588" />
        <bin index="107" start="0.107" width="0.001" count="615" />
        <bin index="108" start="0.108" width="0.001" count="476" />
        <bin index="109" start="0.109" width="0.001" count="278" />
        <bin index="110" start="0.11" width="0.001" count="207" />
        <bin index="111" start="0.111" width="0.001" count="134" />
        <bin index="112" start="0.112" width="0.001" count="44" />
        <bin index="113" start="0.113" width="0.001" count="17" />
        <bin index="115" start="0.115" width="0.001" count="2" />
        <bin index="116" start="0.116" width="0.001" count="2" />
        <bin index="117" start="0.117" width="0.001" count="2" />
        <bin index="118" start="0.118" width="0.001" count="2" />
        <bin index="119" start="0.119" width="0.001" count="2" />
        <bin index="120" start="0.12" width="0.001" count="2" />
        <bin index="121" start="0.121" width="0.001" count="6" />
        <bin index="122" start="0.122" width="0.001" count="2" />
        <bin index="123" start="0.123" width="0.001" count="2" />
        <bin index="124" start="0.124" width="0.001" count="4" />
        <bin index="125" start="0.125" width="0.001" count="5" />
        <bin index="126" start="0.126" width="0.001" count="7" />
        <bin index="127" start="0.127" width="0.001" count="8" />
        <bin index="128" start="0.128" width="0.001" count="19" />
        <bin index="129" start="0.129" width="0.001" count="18" />
        <bin index="130" start="0.13" width="0.001" count="13" />
        <bin index="131" start="0.131" width="0.001" count="2" />
        <bin index="168" start="0.168" width="0.001" count="2" />
        <bin index="170" start="0.17" width="0.001" count="2" />
        <bin index="171" start="0.171" width="0.001" count="2" />
        <bin index="172" start="0.172" width="0.001" count="2" />
        <bin index="173" start="0.173" width="0.001" count="2" />
        <bin index="174" start="0.174" width="0.001" count="2" />
        <bin index="175" start="0.175" width="0.001" count="2" />
        <bin index="176" start="0.176" width="0.001" count="2" />
        <bin index="177" start="0.177" width="0.001" count="2" />
        <bin index="178" start="0.178" width="0.001" count="3" />
        <bin index="179" start="0.179" width="0.001" count="3" />
        <bin index="180" start="0.18" width="0.001" count="4" />
        <bin index="181" start="0.181" width="0.001" count="8" />
        <bin index="182" start="0.182" width="0.001" count="4" />
        <bin index="183" start="0.183" width="0.001" count="4" />
        <bin index="184" start="0.184" width="0.001" count="3" />
        <bin index="185" start="0.185" width="0.001" count="10" />
        <bin index="186" start="0.186" width="0.001" count="10" />
        <bin index="187" start="0.187" width="0.001" count="3" />
        <bin index="188" start="0.188" width="0.001" count="2" />
        <bin index="189" start="0.189" width="0.001" count="2" />
        <bin index="190" start="0.19" width="0.001" count="5" />
        <bin index="191" start="0.191" width="0.001" count="6" />
        <bin index="192" start="0.192" width="0.001" count="3" />
        <bin index="193" start="0.193" width="0.001" count="14" />
        <bin index="194" start="0.194" width="0.001" count="10" />
        <bin index="195" start="0.195" width="0.001" count="5" />
        <bin index="196" start="0.196" width="0.001" count="5" />
        <bin index="197" start="0.197" width="0.001" count="8" />
        <bin index="198" start="0.198" width="0.001" count="6" />
        <bin index="199" start="0.199" width="0.001" count="3" />
        <bin index="203" start="0.203" width="0.001" count="2" />
        <bin index="222" start="0.222" width="0.001" count="2" />
        <bin index="223" start="0.223" width="0.001" count="2" />
        <bin index="224" start="0.224" width="0.001" count="2" />
        <bin index="225" start="0.225" width="0.001" count="2" />
        <bin index="226" start="0.226" width="0.001" count="2" />
        <bin index="227" start="0.227" width="0.001" count="2" />
        <bin index="228" start="0.228" width="0.001" count="2" />
        <bin index="229" start="0.229" width="0.001" count="2" />
        <bin index="230" start="0.23" width="0.001" count="3" />
        <bin index="231" start="0.231" width="0.001" count="6" />
        <bin index="232" start="0.232" width="0.001" count="5" />
        <bin index="233" start="0.233" width="0.001" count="6" />
        <bin index="234" start="0.234" width="0.001" count="1" />
        <bin index="235" start="0.235" width="0.001" count="7" />
        <bin index="236" start="0.236" width="0.001" count="5" />
        <bin index="237" start="0.237" width="0.001" count="2" />
        <bin index="238" start="0.238" width="0.001" count="1" />
      </delayHistogram>
      <jitterHistogram nBins="155" >
        <bin index="0" start="0" width="0.001" count="13111" />
        <bin index="1" start="0.001" width="0.001" count="11446" />
        <bin index="2" start="0.002" width="0.001" count="654" />
        <bin index="3" start="0.003" width="0.001" count="139" />
        <bin index="4" start="0.004" width="0.001" count="159" />
        <bin index="5" start="0.005" width="0.001" count="128" />
        <bin index="6" start="0.006" width="0.001" count="86" />
        <bin index="7" start="0.007" width="0.001" count="70" />
        <bin index="8" start="0.008" width="0.001" count="12" />
        <bin index="9" start="0.009" width="0.001" count="2" />
        <bin index="10" start="0.01" width="0.001" count="3" />
        <bin index="11" start="0.011" width="0.001" count="2" />
        <bin index="13" start="0.013" width="0.001" count="1" />
        <bin index="14" start="0.014" width="0.001" count="2" />
        <bin index="15" start="0.015" width="0.001" count="3" />
        <bin index="16" start="0.016" width="0.001" count="3" />
        <bin index="17" start="0.017" width="0.001" count="5" />
        <bin index="18" start="0.018" width="0.001" count="4" />
        <bin index="19" start="0.019" width="0.001" count="2" />
        <bin index="20" start="0.02" width="0.001" count="5" />
        <bin index="21" start="0.021" width="0.001" count="6" />
        <bin index="22" start="0.022" width="0.001" count="6" />
        <bin index="23" start="0.023" width="0.001" count="7" />
        <bin index="24" start="0.024" width="0.001" count="5" />
        <bin index="25" start="0.025" width="0.001" count="5" />
        <bin index="26" start="0.026" width="0.001" count="3" />
        <bin index="27" start="0.027" width="0.001" count="5" />
        <bin index="28" start="0.028" width="0.001" count="3" />
        <bin index="29" start="0.029" width="0.001" count="6" />
        <bin index="30" start="0.03" width="0.001" count="2" />
        <bin index="31" start="0.031" width="0.001" count="8" />
        <bin index="32" start="0.032" width="0.001" count="3" />
        <bin index="33" start="0.033" width="0.001" count="2" />
        <bin index="34" start="0.034" width="0.001" count="1" />
        <bin index="36" start="0.036" width="0.001" count="1" />
        <bin index="37" start="0.037" width="0.001" count="3" />
        <bin index="38" start="0.038" width="0.001" count="1" />
        <bin index="39" start="0.039" width="0.001" count="3" />
        <bin index="40" start="0.04" width="0.001" count="1" />
        <bin index="41" start="0.041" width="0.001" count="2" />
        <bin index="42" start="0.042" width="0.001" count="1" />
        <bin index="46" start="0.046" width="0.001" count="2" />
        <bin index="47" start="0.047" width="0.001" count="3" />
        <bin index="48" start="0.048" width="0.001" count="3" />
        <bin index="49" start="0.049" width="0.001" count="2" />
        <bin index="50" start="0.05" width="0.001" count="2" />
        <bin index="51" start="0.051" width="0.001" count="5" />
        <bin index="52" start="0.052" width="0.001" count="5" />
        <bin index="53" start="0.053" width="0.001" count="3" />
        <bin index="54" start="0.054" width="0.001" count="11" />
        <bin index="55" start="0.055" width="0.001" count="6" />
        <bin index="56" start="0.056" width="0.001" count="8" />
        <bin index="57" start="0.057" width="0.001" count="7" />
        <bin index="58" start="0.058" width="0.001" count="12" />
        <bin index="59" start="0.059" width="0.001" count="6" />
        <bin index="60" start="0.06" width="0.001" count="11" />
        <bin index="61" start="0.061" width="0.001" count="12" />
        <bin index="62" start="0.062" width="0.001" count="14" />
        <bin index="63" start="0.063" width="0.001" count="13" />
        <bin index="64" start="0.064" width="0.001" count="24" />
        <bin index="65" start="0.065" width="0.001" count="23" />
        <bin index="66" start="0.066" width="0.001" count="9" />
        <bin index="67" start="0.067" width="0.001" count="26" />
        <bin index="68" start="0.068" width="0.001" count="14" />
        <bin index="69" start="0.069" width="0.001" count="11" />
        <bin index="70" start="0.07" width="0.001" count="14" />
        <bin index="71" start="0.071" width="0.001" count="15" />
        <bin index="72" start="0.072" width="0.001" count="20" />
        <bin index="73" start="0.073" width="0.001" count="14" />
        <bin index="74" start="0.074" width="0.001" count="23" />
        <bin index="75" start="0.075" width="0.001" count="20" />
        <bin index="76" start="0.076" width="0.001" count="12" />
        <bin index="77" start="0.077" width="0.001" count="17" />
        <bin index="78" start="0.078" width="0.001" count="12" />
        <bin index="79" start="0.079" width="0.001" count="19" />
        <bin index="80" start="0.08" width="0.001" count="12" />
        <bin index="81" start="0.081" width="0.001" count="22" />
        <bin index="82" start="0.082" width="0.001" count="7" />
        <bin index="83" start="0.083" width="0.001" count="15" />
        <bin index="84" start="0.084" width="0.001" count="12" />
        <bin index="85" start="0.085" width="0.001" count="15" />
        <bin index="86" start="0.086" width="0.001" count="8" />
        <bin index="87" start="0.087" width="0.001" count="4" />
        <bin index="88" start="0.088" width="0.001" count="17" />
        <bin index="89" start="0.089" width="0.001" count="11" />
        <bin index="90" start="0.09" width="0.001" count="8" />
        <bin index="91" start="0.091" width="0.001" count="9" />
        <bin index="92" start="0.092" width="0.001" count="6" />
        <bin index="93" start="0.093" width="0.001" count="10" />
        <bin index="94" start="0.094" width="0.001" count="5" />
        <bin index="95" start="0.095" width="0.001" count="6" />
        <bin index="96" start="0.096" width="0.001" count="4" />
        <bin index="97" start="0.097" width="0.001" count="4" />
        <bin index="98" start="0.098" width="0.001" count="2" />
        <bin index="99" start="0.099" width="0.001" count="3" />
        <bin index="100" start="0.1" width="0.001" count="1" />
        <bin index="101" start="0.101" width="0.001" count="2" />
        <bin index="102" start="0.102" width="0.001" count="3" />
        <bin index="154" start="0.154" width="0.001" count="1" />
      </jitterHistogram>
      <packetSizeHistogram nBins="30" >
        <bin index="2" start="40" width="20" count="1" />
        <bin index="4" start="80" width="20" count="3" />
        <bin index="11" start="220" width="20" count="1" />
        <bin index="16" start="320" width="20" count="1" />
        <bin index="17" start="340" width="20" count="1" />
        <bin index="29" start="580" width="20" count="26490" />
      </packetSizeHistogram>
      <flowInterruptionsHistogram nBins="0" >
      </flowInterruptionsHistogram>
    </Flow>
    <Flow flowId="13" timeFirstTxPacket="+3034958387.0ns" timeFirstRxPacket="+4325679000.0ns" timeLastTxPacket="+3034958387.0ns" timeLastRxPacket="+4325679000.0ns" delaySum="+1290720613.0ns" jitterSum="+0.0ns" lastDelay="+1290720613.0ns" txBytes="94" rxBytes="94" txPackets="1" rxPackets="1" lostPackets="0" timesForwarded="1">
      <delayHistogram nBins="1291" >
        <bin index="1290" start="1.29" width="0.001" count="1" />
      </delayHistogram>
      <jitterHistogram nBins="0" >
      </jitterHistogram>
      <packetSizeHistogram nBins="5" >
        <bin index="4" start="80" width="20" count="1" />
      </packetSizeHistogram>
      <flowInterruptionsHistogram nBins="0" >
      </flowInterruptionsHistogram>
    </Flow>
    <Flow flowId="14" timeFirstTxPacket="+3035009906.0ns" timeFirstRxPacket="+3039606000.0ns" timeLastTxPacket="+3035009906.0ns" timeLastRxPacket="+3039606000.0ns" delaySum="+4596094.0ns" jitterSum="+0.0ns" lastDelay="+4596094.0ns" txBytes="94" rxBytes="94" txPackets="1" rxPackets="1" lostPackets="0" timesForwarded="1">
      <delayHistogram nBins="5" >
        <bin index="4" start="0.004" width="0.001" count="1" />
      </delayHistogram>
      <jitterHistogram nBins="0" >
      </jitterHistogram>
      <packetSizeHistogram nBins="5" >
        <bin index="4" start="80" width="20" count="1" />
      </packetSizeHistogram>
      <flowInterruptionsHistogram nBins="0" >
      </flowInterruptionsHistogram>
    </Flow>
    <Flow flowId="15" timeFirstTxPacket="+3035061425.0ns" timeFirstRxPacket="+3037650000.0ns" timeLastTxPacket="+3035061425.0ns" timeLastRxPacket="+3037650000.0ns" delaySum="+2588575.0ns" jitterSum="+0.0ns" lastDelay="+2588575.0ns" txBytes="94" rxBytes="94" txPackets="1" rxPackets="1" lostPackets="0" timesForwarded="1">
      <delayHistogram nBins="3" >
        <bin index="2" start="0.002" width="0.001" count="1" />
      </delayHistogram>
      <jitterHistogram nBins="0" >
      </jitterHistogram>
      <packetSizeHistogram nBins="5" >
        <bin index="4" start="80" width="20" count="1" />
      </packetSizeHistogram>
      <flowInterruptionsHistogram nBins="0" >
      </flowInterruptionsHistogram>
    </Flow>
    <Flow flowId="16" timeFirstTxPacket="+3035112944.0ns" timeFirstRxPacket="+3042863000.0ns" timeLastTxPacket="+3035112944.0ns" timeLastRxPacket="+3042863000.0ns" delaySum="+7750056.0ns" jitterSum="+0.0ns" lastDelay="+7750056.0ns" txBytes="94" rxBytes="94" txPackets="1" rxPackets="1" lostPackets="0" timesForwarded="1">
      <delayHistogram nBins="8" >
        <bin index="7" start="0.007" width="0.001" count="1" />
      </delayHistogram>
      <jitterHistogram nBins="0" >
      </jitterHistogram>
      <packetSizeHistogram nBins="5" >
        <bin index="4" start="80" width="20" count="1" />
      </packetSizeHistogram>
      <flowInterruptionsHistogram nBins="0" >
      </flowInterruptionsHistogram>
    </Flow>
  </FlowStats>
  <Ipv4FlowClassifier>
    <Flow flowId="1" sourceAddress="7.0.0.2" destinationAddress="10.1.4.1" protocol="6" sourcePort="49153" destinationPort="80">
      <Dscp value="0x0" packets="9431" />
    </Flow>
    <Flow flowId="2" sourceAddress="7.0.0.3" destinationAddress="10.1.4.1" protocol="6" sourcePort="49153" destinationPort="80">
      <Dscp value="0x0" packets="16785" />
    </Flow>
    <Flow flowId="3" sourceAddress="7.0.0.4" destinationAddress="10.1.4.1" protocol="6" sourcePort="49153" destinationPort="80">
      <Dscp value="0x0" packets="13453" />
    </Flow>
    <Flow flowId="4" sourceAddress="7.0.0.5" destinationAddress="10.1.4.1" protocol="6" sourcePort="49153" destinationPort="80">
      <Dscp value="0x0" packets="13624" />
    </Flow>
    <Flow flowId="9" sourceAddress="10.1.4.1" destinationAddress="7.0.0.2" protocol="6" sourcePort="80" destinationPort="49153">
      <Dscp value="0x0" packets="18423" />
    </Flow>
    <Flow flowId="10" sourceAddress="10.1.4.1" destinationAddress="7.0.0.3" protocol="6" sourcePort="80" destinationPort="49153">
      <Dscp value="0x0" packets="32892" />
    </Flow>
    <Flow flowId="11" sourceAddress="10.1.4.1" destinationAddress="7.0.0.4" protocol="6" sourcePort="80" destinationPort="49153">
      <Dscp value="0x0" packets="26070" />
    </Flow>
    <Flow flowId="12" sourceAddress="10.1.4.1" destinationAddress="7.0.0.5" protocol="6" sourcePort="80" destinationPort="49153">
      <Dscp value="0x0" packets="26559" />
    </Flow>
    <Flow flowId="5" sourceAddress="13.0.0.5" destinationAddress="13.0.0.6" protocol="17" sourcePort="2123" destinationPort="2123">
      <Dscp value="0x0" packets="4" />
    </Flow>
    <Flow flowId="8" sourceAddress="13.0.0.6" destinationAddress="13.0.0.5" protocol="17" sourcePort="2123" destinationPort="2123">
      <Dscp value="0x0" packets="4" />
    </Flow>
    <Flow flowId="7" sourceAddress="14.0.0.5" destinationAddress="14.0.0.6" protocol="17" sourcePort="2123" destinationPort="2123">
      <Dscp value="0x0" packets="4" />
    </Flow>
    <Flow flowId="6" sourceAddress="14.0.0.6" destinationAddress="14.0.0.5" protocol="17" sourcePort="2123" destinationPort="2123">
      <Dscp value="0x0" packets="4" />
    </Flow>
    <Flow flowId="13" sourceAddress="20.1.2.1" destinationAddress="10.1.2.3" protocol="17" sourcePort="49153" destinationPort="9">
      <Dscp value="0x0" packets="1" />
    </Flow>
    <Flow flowId="14" sourceAddress="20.1.2.1" destinationAddress="10.1.2.4" protocol="17" sourcePort="49154" destinationPort="9">
      <Dscp value="0x0" packets="1" />
    </Flow>
    <Flow flowId="15" sourceAddress="20.1.2.1" destinationAddress="10.1.2.5" protocol="17" sourcePort="49155" destinationPort="9">
      <Dscp value="0x0" packets="1" />
    </Flow>
    <Flow flowId="16" sourceAddress="20.1.2.1" destinationAddress="10.1.2.6" protocol="17" sourcePort="49156" destinationPort="9">
      <Dscp value="0x0" packets="1" />
    </Flow>
  </Ipv4FlowClassifier>
  <Ipv6FlowClassifier>
  </Ipv6FlowClassifier>
  <FlowProbes>
    <FlowProbe index="0">
      <FlowStats  flowId="1" packets="9430" bytes="497351" delayFromFirstProbeSum="+86161687762.0ns" >
      </FlowStats>
      <FlowStats  flowId="2" packets="16784" bytes="884062" delayFromFirstProbeSum="+145266280935.0ns" >
      </FlowStats>
      <FlowStats  flowId="3" packets="13445" bytes="711432" delayFromFirstProbeSum="+118179739504.0ns" >
      </FlowStats>
      <FlowStats  flowId="4" packets="13623" bytes="720826" delayFromFirstProbeSum="+119498181483.0ns" >
      </FlowStats>
      <FlowStats  flowId="9" packets="18423" bytes="10829828" delayFromFirstProbeSum="+0.0ns" >
      </FlowStats>
      <FlowStats  flowId="10" packets="32892" bytes="19336942" delayFromFirstProbeSum="+0.0ns" >
      </FlowStats>
      <FlowStats  flowId="11" packets="26070" bytes="15326299" delayFromFirstProbeSum="+0.0ns" >
      </FlowStats>
      <FlowStats  flowId="12" packets="26559" bytes="15613290" delayFromFirstProbeSum="+0.0ns" >
      </FlowStats>
    </FlowProbe>
    <FlowProbe index="1">
    </FlowProbe>
    <FlowProbe index="2">
      <FlowStats  flowId="13" packets="1" bytes="94" delayFromFirstProbeSum="+7679.0ns" >
      </FlowStats>
      <FlowStats  flowId="14" packets="1" bytes="94" delayFromFirstProbeSum="+7679.0ns" >
      </FlowStats>
      <FlowStats  flowId="15" packets="1" bytes="94" delayFromFirstProbeSum="+7679.0ns" >
      </FlowStats>
      <FlowStats  flowId="16" packets="1" bytes="94" delayFromFirstProbeSum="+7679.0ns" >
      </FlowStats>
    </FlowProbe>
    <FlowProbe index="3">
    </FlowProbe>
    <FlowProbe index="4">
    </FlowProbe>
    <FlowProbe index="5">
    </FlowProbe>
    <FlowProbe index="6">
      <FlowStats  flowId="1" packets="9431" bytes="497407" delayFromFirstProbeSum="+0.0ns" >
      </FlowStats>
      <FlowStats  flowId="9" packets="18380" bytes="10805080" delayFromFirstProbeSum="+1669239163005.0ns" >
      </FlowStats>
      <FlowStats  flowId="13" packets="1" bytes="94" delayFromFirstProbeSum="+1290720613.0ns" >
      </FlowStats>
    </FlowProbe>
    <FlowProbe index="7">
    </FlowProbe>
    <FlowProbe index="8">
      <FlowStats  flowId="2" packets="16785" bytes="884118" delayFromFirstProbeSum="+0.0ns" >
      </FlowStats>
      <FlowStats  flowId="10" packets="32813" bytes="19291026" delayFromFirstProbeSum="+2983596713168.0ns" >
      </FlowStats>
      <FlowStats  flowId="14" packets="1" bytes="94" delayFromFirstProbeSum="+4596094.0ns" >
      </FlowStats>
    </FlowProbe>
    <FlowProbe index="9">
    </FlowProbe>
    <FlowProbe index="10">
      <FlowStats  flowId="3" packets="13453" bytes="711852" delayFromFirstProbeSum="+0.0ns" >
      </FlowStats>
      <FlowStats  flowId="11" packets="26033" bytes="15305079" delayFromFirstProbeSum="+2378370809866.0ns" >
      </FlowStats>
      <FlowStats  flowId="15" packets="1" bytes="94" delayFromFirstProbeSum="+2588575.0ns" >
      </FlowStats>
    </FlowProbe>
    <FlowProbe index="11">
    </FlowProbe>
    <FlowProbe index="12">
      <FlowStats  flowId="4" packets="13624" bytes="720882" delayFromFirstProbeSum="+0.0ns" >
      </FlowStats>
      <FlowStats  flowId="12" packets="26497" bytes="15577370" delayFromFirstProbeSum="+2416917440976.0ns" >
      </FlowStats>
      <FlowStats  flowId="16" packets="1" bytes="94" delayFromFirstProbeSum="+7750056.0ns" >
      </FlowStats>
    </FlowProbe>
    <FlowProbe index="13">
    </FlowProbe>
    <FlowProbe index="14">
    </FlowProbe>
    <FlowProbe index="15">
    </FlowProbe>
    <FlowProbe index="16">
      <FlowStats  flowId="13" packets="1" bytes="94" delayFromFirstProbeSum="+0.0ns" >
      </FlowStats>
      <FlowStats  flowId="14" packets="1" bytes="94" delayFromFirstProbeSum="+0.0ns" >
      </FlowStats>
      <FlowStats  flowId="15" packets="1" bytes="94" delayFromFirstProbeSum="+0.0ns" >
      </FlowStats>
      <FlowStats  flowId="16" packets="1" bytes="94" delayFromFirstProbeSum="+0.0ns" >
      </FlowStats>
    </FlowProbe>
    <FlowProbe index="17">
    </FlowProbe>
    <FlowProbe index="18">
      <FlowStats  flowId="1" packets="9430" bytes="497351" delayFromFirstProbeSum="+67192461199.0ns" >
      </FlowStats>
      <FlowStats  flowId="2" packets="16784" bytes="884062" delayFromFirstProbeSum="+111528738948.0ns" >
      </FlowStats>
      <FlowStats  flowId="3" packets="13446" bytes="711484" delayFromFirstProbeSum="+91151472463.0ns" >
      </FlowStats>
      <FlowStats  flowId="4" packets="13623" bytes="720826" delayFromFirstProbeSum="+92108152322.0ns" >
      </FlowStats>
      <FlowStats  flowId="6" packets="4" bytes="656" delayFromFirstProbeSum="+528.0ns" >
      </FlowStats>
      <FlowStats  flowId="7" packets="4" bytes="584" delayFromFirstProbeSum="+0.0ns" >
      </FlowStats>
      <FlowStats  flowId="9" packets="18423" bytes="10829828" delayFromFirstProbeSum="+40988991026.0ns" >
      </FlowStats>
      <FlowStats  flowId="10" packets="32892" bytes="19336942" delayFromFirstProbeSum="+72465707559.0ns" >
      </FlowStats>
      <FlowStats  flowId="11" packets="26054" bytes="15316891" delayFromFirstProbeSum="+57663077700.0ns" >
      </FlowStats>
      <FlowStats  flowId="12" packets="26559" bytes="15613290" delayFromFirstProbeSum="+58727767538.0ns" >
      </FlowStats>
    </FlowProbe>
    <FlowProbe index="19">
    </FlowProbe>
    <FlowProbe index="20">
      <FlowStats  flowId="5" packets="4" bytes="656" delayFromFirstProbeSum="+1320.0ns" >
      </FlowStats>
      <FlowStats  flowId="6" packets="4" bytes="656" delayFromFirstProbeSum="+0.0ns" >
      </FlowStats>
      <FlowStats  flowId="7" packets="4" bytes="584" delayFromFirstProbeSum="+472.0ns" >
      </FlowStats>
      <FlowStats  flowId="8" packets="4" bytes="584" delayFromFirstProbeSum="+0.0ns" >
      </FlowStats>
    </FlowProbe>
    <FlowProbe index="21">
    </FlowProbe>
    <FlowProbe index="22">
      <FlowStats  flowId="5" packets="4" bytes="656" delayFromFirstProbeSum="+0.0ns" >
      </FlowStats>
      <FlowStats  flowId="8" packets="4" bytes="584" delayFromFirstProbeSum="+472.0ns" >
      </FlowStats>
    </FlowProbe>
    <FlowProbe index="23">
    </FlowProbe>
  </FlowProbes>
</FlowMonitor>
